MANIFEST.in
setup.cfg
setup.py
bplib/__init__.py
bplib/bindings.py
bplib/bp.py
bplib/compile.py
bplib.egg-info/PKG-INFO
bplib.egg-info/SOURCES.txt
bplib.egg-info/dependency_links.txt
bplib.egg-info/not-zip-safe
bplib.egg-info/requires.txt
bplib.egg-info/top_level.txt
bplib/src/bp_fp12.c
bplib/src/bp_fp2.c
bplib/src/bp_fp6.c
bplib/src/bp_g1.c
bplib/src/bp_g2.c
bplib/src/bp_g2_mult.c
bplib/src/bp_group.c
bplib/src/bp_gt.c
bplib/src/bp_map.c
examples/PSSig.py
include/bp.h
include/bp_lcl.h