Metadata-Version: 1.0
Name: bplib
Version: 0.0.1
Summary: A bilinear pairing library for petlib.
Home-page: https://pypi.python.org/pypi/bplib/
Author: George Danezis
Author-email: g.danezis@ucl.ac.uk
License: LGPL
Platform: UNKNOWN
